jarviscg/__init__.py
jarviscg/cli.py
jarviscg/core.py
jarviscg/formats/__init__.py
jarviscg/formats/as_graph.py
jarviscg/formats/base.py
jarviscg/formats/nuanced.py
jarviscg/formats/simple.py
jarviscg/machinery/__init__.py
jarviscg/machinery/callgraph.py
jarviscg/machinery/calls.py
jarviscg/machinery/changes.py
jarviscg/machinery/classes.py
jarviscg/machinery/definitions.py
jarviscg/machinery/gol.py
jarviscg/machinery/imports.py
jarviscg/machinery/key_err.py
jarviscg/machinery/modules.py
jarviscg/machinery/nodes.py
jarviscg/machinery/pointers.py
jarviscg/machinery/returns.py
jarviscg/machinery/scopes.py
jarviscg/processing/__init__.py
jarviscg/processing/base.py
jarviscg/processing/extProcessor.py
jarviscg/utils/__init__.py
jarviscg/utils/common.py
jarviscg/utils/constants.py
jarviscg-0.1.0rc7.dist-info/METADATA
jarviscg-0.1.0rc7.dist-info/WHEEL
jarviscg-0.1.0rc7.dist-info/entry_points.txt
jarviscg-0.1.0rc7.dist-info/RECORD
