Metadata-Version: 2.4
Name: jarviscg
Version: 0.1.0rc7
Summary: Call graph generator for Python forked from pythonJaRvis/pythonJaRvis.github.io
Author-email: Ayman Nadeem <ayman@nuanced.dev>
Requires-Python: >=3.8
Requires-Dist: deepdiff>=8.2.0
Requires-Dist: pytest>=8.3.4
Requires-Dist: setuptools>=75.3.0
